{
  "group_interval": 1000,
  "host": {
    "name": "IP Address",
    "name_zh": "IP地址",
    "description": "Local IP in server mode, remote device IP in client mode",
    "description_zh": "服务端模式中填写本地 IP，客户端模式中填写目标设备 IP",
    "default": "192.168.1.2",
    "attribute": "required",
    "type": "string"
  },
  "port": {
    "name": "Port",
    "name_zh": "端口号",
    "description": "Local port in server mode, remote device port in client mode",
    "description_zh": "PLC EtherNet/IP CIP 端口号",
    "attribute": "required",
    "type": "int",
    "default": 44818,
    "valid": {
      "min": 1,
      "max": 65535
    }
  },
  "timeout": {
    "name": "Connection Timeout",
    "name_zh": "连接超时时间",
    "description": "Connection timeout(ms)",
    "description_zh": "连接超时时间，单位为毫秒",
    "attribute": "required",
    "type": "int",
    "default": 2000,
    "valid": {
      "min": 500,
      "max": 60000
    }
  }
}